CHANGES.txt
LICENSE
MANIFEST.in
README.rst
requirements.txt
setup.py
LICENSES/NUMPY_LICENSE
LICENSES/SIX_LICENSE
dummy_package/__init__.py
dummy_package/utils.py
dummy_package.egg-info/PKG-INFO
dummy_package.egg-info/SOURCES.txt
dummy_package.egg-info/dependency_links.txt
dummy_package.egg-info/not-zip-safe
dummy_package.egg-info/requires.txt
dummy_package.egg-info/top_level.txt
dummy_package/similarity_measure/__init__.py
dummy_package/similarity_measure/affine.py
dummy_package/similarity_measure/cosine.py
dummy_package/similarity_measure/cython_levenshtein.c
dummy_package/similarity_measure/dice.py
dummy_package/similarity_measure/hamming_distance.py
dummy_package/similarity_measure/hybrid_similarity_measure.py
dummy_package/similarity_measure/jaccard.py
dummy_package/similarity_measure/jaro.py
dummy_package/similarity_measure/jaro_winkler.py
dummy_package/similarity_measure/levenshtein.py
dummy_package/similarity_measure/monge_elkan.py
dummy_package/similarity_measure/needleman_wunsch.py
dummy_package/similarity_measure/overlap_coefficient.py
dummy_package/similarity_measure/sequence_similarity_measure.py
dummy_package/similarity_measure/similarity_measure.py
dummy_package/similarity_measure/smith_waterman.py
dummy_package/similarity_measure/soft_tfidf.py
dummy_package/similarity_measure/tfidf.py
dummy_package/similarity_measure/token_similarity_measure.py
dummy_package/tests/__init__.py
dummy_package/tests/test_simfunctions.py
dummy_package/tests/test_tokenizers.py
dummy_package/tokenizer/__init__.py
dummy_package/tokenizer/alphabetic_tokenizer.py
dummy_package/tokenizer/alphanumeric_tokenizer.py
dummy_package/tokenizer/definition_tokenizer.py
dummy_package/tokenizer/delimiter_tokenizer.py
dummy_package/tokenizer/qgram_tokenizer.py
dummy_package/tokenizer/tokenizer.py
dummy_package/tokenizer/whitespace_tokenizer.py